agenius/__init__.py
agenius/errors.py
agenius/main.py
agenius/api_calls/__init__.py
agenius/api_calls/api.py
agenius/api_calls/base.py
agenius/class_types/__init__.py
agenius/class_types/album.py
agenius/class_types/artist.py
agenius/class_types/base.py
agenius/class_types/song.py
agenius-4.0.2.dist-info/COPYING
agenius-4.0.2.dist-info/COPYING.LESSER
agenius-4.0.2.dist-info/COPYING.ORIGINAL.txt
agenius-4.0.2.dist-info/LICENSE.md
agenius-4.0.2.dist-info/METADATA
agenius-4.0.2.dist-info/WHEEL
agenius-4.0.2.dist-info/top_level.txt
agenius-4.0.2.dist-info/RECORD
