Metadata-Version: 2.1
Name: agenius
Version: 4.0.2
Summary: A LyricsGenius fork with async ready features.
Home-page: https://github.com/dopebnan/AGenius.py
Author: dopebnan
Author-email: 82271322+dopebnan@users.noreply.github.com
License: LGPLv3+
Project-URL: Bug Tracker, https://github.com/dopebnan/AGenius.py/issues
Classifier: Programming Language :: Python :: 3.9
Classifier: Programming Language :: Python :: 3.8
Classifier: Programming Language :: Python :: 3.7
Classifier: Development Status :: 5 - Production/Stable
Classifier: License :: OSI Approved :: GNU Lesser General Public License v3 (LGPLv3)
Classifier: Topic :: Software Development :: Libraries
Classifier: Topic :: Software Development :: Libraries :: Application Frameworks
Classifier: Topic :: Software Development :: Libraries :: Python Modules
Classifier: Operating System :: OS Independent
Requires-Python: >=3.7
License-File: LICENSE.md
License-File: COPYING
License-File: COPYING.LESSER
License-File: COPYING.ORIGINAL.txt
Requires-Dist: beautifulsoup4 >=4.6.0
Requires-Dist: aiohttp <4,>=3.6.0
